XuniHuobiTouziShizhanJiqiao/README.md
XuniHuobiTouziShizhanJiqiao/__init__.py
XuniHuobiTouziShizhanJiqiao/__main__.py
XuniHuobiTouziShizhanJiqiao/file.epub
XuniHuobiTouziShizhanJiqiao/index.html
XuniHuobiTouziShizhanJiqiao/css/__init__.py
XuniHuobiTouziShizhanJiqiao/css/annotations.css
XuniHuobiTouziShizhanJiqiao/css/main.css
XuniHuobiTouziShizhanJiqiao/css/normalize.css
XuniHuobiTouziShizhanJiqiao/css/popup.css
XuniHuobiTouziShizhanJiqiao/font/__init__.py
XuniHuobiTouziShizhanJiqiao/font/fontello.eot
XuniHuobiTouziShizhanJiqiao/font/fontello.svg
XuniHuobiTouziShizhanJiqiao/font/fontello.ttf
XuniHuobiTouziShizhanJiqiao/font/fontello.woff
XuniHuobiTouziShizhanJiqiao/img/__init__.py
XuniHuobiTouziShizhanJiqiao/img/annotator-glyph-sprite.png
XuniHuobiTouziShizhanJiqiao/img/annotator-icon-sprite.png
XuniHuobiTouziShizhanJiqiao/img/apple-touch-icon.png
XuniHuobiTouziShizhanJiqiao/img/cancelfullscreen.png
XuniHuobiTouziShizhanJiqiao/img/close.png
XuniHuobiTouziShizhanJiqiao/img/fullscreen.png
XuniHuobiTouziShizhanJiqiao/img/loader.gif
XuniHuobiTouziShizhanJiqiao/img/menu-icon.png
XuniHuobiTouziShizhanJiqiao/img/save.png
XuniHuobiTouziShizhanJiqiao/img/saved.png
XuniHuobiTouziShizhanJiqiao/img/settings-s.png
XuniHuobiTouziShizhanJiqiao/img/settings.png
XuniHuobiTouziShizhanJiqiao/img/star.png
XuniHuobiTouziShizhanJiqiao/js/__init__.py
XuniHuobiTouziShizhanJiqiao/js/epub.js
XuniHuobiTouziShizhanJiqiao/js/epub.min.js
XuniHuobiTouziShizhanJiqiao/js/epub.min.map
XuniHuobiTouziShizhanJiqiao/js/hooks.min.js
XuniHuobiTouziShizhanJiqiao/js/hooks.min.map
XuniHuobiTouziShizhanJiqiao/js/reader.js
XuniHuobiTouziShizhanJiqiao/js/reader.js.map
XuniHuobiTouziShizhanJiqiao/js/reader.min.js
XuniHuobiTouziShizhanJiqiao/js/reader.min.map
XuniHuobiTouziShizhanJiqiao/js/hooks/__init__.py
XuniHuobiTouziShizhanJiqiao/js/hooks/extensions/__init__.py
XuniHuobiTouziShizhanJiqiao/js/hooks/extensions/highlight.js
XuniHuobiTouziShizhanJiqiao/js/libs/__init__.py
xuni_huobi_touzi_shizhan_jiqiao-2024.3.3.0.dist-info/METADATA
xuni_huobi_touzi_shizhan_jiqiao-2024.3.3.0.dist-info/WHEEL
xuni_huobi_touzi_shizhan_jiqiao-2024.3.3.0.dist-info/entry_points.txt
xuni_huobi_touzi_shizhan_jiqiao-2024.3.3.0.dist-info/top_level.txt
xuni_huobi_touzi_shizhan_jiqiao-2024.3.3.0.dist-info/RECORD
